{
    "3" : {
        "title" : "CLB Barcelona dưới triều đại Johan Cruyff và bài học kinh nghiệm cho bóng đá Việt Nam",
        "date" : "01/06/2023",
        "image" : "https://dd20lazkioz9n.cloudfront.net/wp-content/uploads/2021/06/LaMasiaseries.jpg", 
        "author" : "Nguyễn Hoàng Phúc"
    },
    "2" : {
        "title" : "CLB Barcelona dưới triều đại Johan Cruyff và bài học kinh nghiệm cho bóng đá Việt Nam",
        "date" : "01/06/2023",
        "image" : "https://dd20lazkioz9n.cloudfront.net/wp-content/uploads/2021/06/LaMasiaseries.jpg", 
        "author" : "Nguyễn Hoàng Phúc"
    },
    "1" : {
        "title" : "CLB Barcelona dưới triều đại Johan Cruyff và bài học kinh nghiệm cho bóng đá Việt Nam",
        "date" : "01/06/2023",
        "image" : "https://dd20lazkioz9n.cloudfront.net/wp-content/uploads/2021/06/LaMasiaseries.jpg", 
        "author" : "Nguyễn Hoàng Phúc"
    }
}